wqsketch/__init__.py
wqsketch/wqsketch.py
wqsketch-0.0.2.dist-info/METADATA
wqsketch-0.0.2.dist-info/WHEEL
wqsketch-0.0.2.dist-info/top_level.txt
wqsketch-0.0.2.dist-info/RECORD
