Metadata-Version: 2.1
Name: wqsketch
Version: 0.0.2
Summary: Weighted Quantile Sketch
Home-page: UNKNOWN
Author: Benjamin Tay
Author-email: <benjamin.tay85@gmail.com>
License: UNKNOWN
Keywords: weighted,quantile,sketch,mergeable
Platform: UNKNOWN
Classifier: Development Status :: 1 - Planning
Classifier: Intended Audience :: Developers
Classifier: Programming Language :: Python :: 3
Classifier: Operating System :: Unix
Classifier: Operating System :: MacOS :: MacOS X
Classifier: Operating System :: Microsoft :: Windows
Requires-Dist: numpy
